kition_djangodefaults/__init__.py
kition_djangodefaults/apps.py
kition_djangodefaults/healthcheck.py
kition_djangodefaults/logging.py
kition_djangodefaults/management/__init__.py
kition_djangodefaults/management/commands/__init__.py
kition_djangodefaults/management/commands/sendtestmail.py
kition_djangodefaults/py.typed
kition_djangodefaults/settings/__init__.py
kition_djangodefaults/settings/default.py
kition_djangodefaults/settings/default_basedir.py
kition_djangodefaults/settings/util.py
kition_djangodefaults-0.5.2.dist-info/METADATA
kition_djangodefaults-0.5.2.dist-info/WHEEL
kition_djangodefaults-0.5.2.dist-info/licenses/LICENSE
kition_djangodefaults-0.5.2.dist-info/RECORD
