Metadata-Version: 2.4
Name: kition-djangodefaults
Version: 0.5.2
Summary: Default configuration and components for Django projects.
License-Expression: MIT
License-File: LICENSE
Author: Dennis Stritzke
Author-email: dennis.stritzke@kition.dev
Requires-Python: >=3.12,<4
Classifier: Programming Language :: Python :: 3
Classifier: Programming Language :: Python :: 3.12
Classifier: Programming Language :: Python :: 3.13
Classifier: Programming Language :: Python :: 3.14
Provides-Extra: dev
Provides-Extra: worker
Requires-Dist: django (>=5.1)
Requires-Dist: django-q2 (>=1.9,<2.0) ; extra == "worker"
Requires-Dist: django-storages[s3] (>=1.14,<2.0)
Requires-Dist: django-stubs (==5.2.8) ; extra == "dev"
Requires-Dist: mypy (==1.19.1) ; extra == "dev"
Requires-Dist: psycopg (>=3.2,<4.0)
Requires-Dist: ruff (==0.14.10) ; extra == "dev"
Project-URL: Changelog, https://github.com/kition-dev/djangodefaults/blob/main/CHANGELOG.md
Project-URL: Issues, https://github.com/kition-dev/djangodefaults/issues
Project-URL: Source, https://github.com/kition-dev/djangodefaults
